pip_sequencer/__init__.py
pip_sequencer/cli.py
pip_sequencer/history.py
pip_sequencer/recorder.py
pip_sequencer-0.6.1.dist-info/METADATA
pip_sequencer-0.6.1.dist-info/WHEEL
pip_sequencer-0.6.1.dist-info/entry_points.txt
pip_sequencer-0.6.1.dist-info/top_level.txt
pip_sequencer-0.6.1.dist-info/RECORD
