Metadata-Version: 2.4
Name: pip-sequencer
Version: 0.6.1
Summary: Record, replay, and export pip installation/uninstallation sequences.
Author-email: Rachill007 <rahilmaniar18@gmail.com>
Project-URL: Homepage, https://github.com/Rahil-Maniar/pip-sequencer
Project-URL: Repository, https://github.com/Rahil-Maniar/pip-sequencer
Project-URL: Bug Tracker, https://github.com/Rahil-Maniar/pip-sequencer/issues
Keywords: pip,virtualenv,uv,venv,version conflicts,package management,requirements,sequence,order,install,uninstall,dependencies,reproducible,environment,backend
Classifier: Development Status :: 5 - Production/Stable
Classifier: Intended Audience :: Developers
Classifier: Intended Audience :: System Administrators
Classifier: Topic :: Software Development :: Build Tools
Classifier: Topic :: System :: Archiving :: Packaging
Classifier: Topic :: Utilities
Classifier: Programming Language :: Python :: 3
Classifier: Programming Language :: Python :: 3.7
Classifier: Programming Language :: Python :: 3.8
Classifier: Programming Language :: Python :: 3.9
Classifier: Programming Language :: Python :: 3.10
Classifier: Programming Language :: Python :: 3.11
Classifier: Programming Language :: Python :: 3.12
Classifier: Operating System :: OS Independent
Classifier: Environment :: Console
Requires-Python: >=3.7
Requires-Dist: setuptools
